f_codec-0.1.0.data/data/lib/python/site-packages/fcodec.pth
fcodec/__init__.py
f_codec-0.1.0.dist-info/LICENSE
f_codec-0.1.0.dist-info/METADATA
f_codec-0.1.0.dist-info/WHEEL
f_codec-0.1.0.dist-info/top_level.txt
f_codec-0.1.0.dist-info/RECORD
