Metadata-Version: 2.1
Name: f-codec
Version: 0.1.0
Summary: Python 'f' Codec
Home-page: https://github.com/in4lio/f-codec
Author: Vitaly Kravtsov
Author-email: in4lio@gmail.com
License: UNKNOWN
Platform: any
Classifier: Programming Language :: Python :: 3
Classifier: License :: OSI Approved :: MIT License
Classifier: Operating System :: OS Independent
Requires-Python: >=3.6
